lang_pref_middleware/__init__.py
lang_pref_middleware/middleware.py
lang_pref_middleware/tests.py
django_lang_pref_middleware-1.3.0.dist-info/AUTHORS
django_lang_pref_middleware-1.3.0.dist-info/LICENSE.txt
django_lang_pref_middleware-1.3.0.dist-info/METADATA
django_lang_pref_middleware-1.3.0.dist-info/NOTICE.txt
django_lang_pref_middleware-1.3.0.dist-info/WHEEL
django_lang_pref_middleware-1.3.0.dist-info/top_level.txt
django_lang_pref_middleware-1.3.0.dist-info/RECORD
