Metadata-Version: 2.1
Name: django-lang-pref-middleware
Version: 1.3.0
Summary: Django middleware for setting the user's language preference at request time.
Home-page: https://github.com/openedx/django-lang-pref-middleware
Author: edX
Author-email: oscm@edx.org
Classifier: Intended Audience :: Developers
Classifier: License :: OSI Approved :: Apache Software License
Classifier: Operating System :: OS Independent
Classifier: Framework :: Django
Classifier: Framework :: Django :: 3.2
Classifier: Framework :: Django :: 4.2
Classifier: Programming Language :: Python :: 3
Classifier: Programming Language :: Python :: 3.8
License-File: LICENSE.txt
License-File: NOTICE.txt
License-File: AUTHORS
Requires-Dist: django
